CHANGES.txt
MANIFEST.in
README.md
setup.cfg
setup.py
penelope/__init__.py
penelope.core.egg-info/PKG-INFO
penelope.core.egg-info/SOURCES.txt
penelope.core.egg-info/dependency_links.txt
penelope.core.egg-info/entry_points.txt
penelope.core.egg-info/namespace_packages.txt
penelope.core.egg-info/not-zip-safe
penelope.core.egg-info/requires.txt
penelope.core.egg-info/top_level.txt
penelope/core/__init__.py
penelope/core/activity_stream.py
penelope/core/api.py
penelope/core/backlog.py
penelope/core/breadcrumbs.py
penelope/core/build_18n_po.sh
penelope/core/events.py
penelope/core/fanstatic_resources.py
penelope/core/html2text.py
penelope/core/interfaces.py
penelope/core/kanbanboard.py
penelope/core/manage.py
penelope/core/messages.py
penelope/core/ravenlog.py
penelope/core/renderers.py
penelope/core/search.py
penelope/core/sidebar.py
penelope/core/smartadd.py
penelope/core/socketspace.py
penelope/core/tp.py
penelope/core/views.py
penelope/core/workflow.zcml
penelope/core/deform_templates/chosen_multiple.pt
penelope/core/deform_templates/dateinput.pt
penelope/core/deform_templates/form.pt
penelope/core/deform_templates/mapping_item.pt
penelope/core/deform_templates/textinput.pt
penelope/core/forms/__init__.py
penelope/core/forms/application.py
penelope/core/forms/application_views.py
penelope/core/forms/contract.py
penelope/core/forms/cost.py
penelope/core/forms/customer.py
penelope/core/forms/customer_request.py
penelope/core/forms/fast_ticketing.py
penelope/core/forms/group.py
penelope/core/forms/kanbanboard.py
penelope/core/forms/project.py
penelope/core/forms/renderers.py
penelope/core/forms/role.py
penelope/core/forms/timeentry.py
penelope/core/forms/user.py
penelope/core/forms/wizard.py
penelope/core/forms/workflow.py
penelope/core/forms/templates/add_project.pt
penelope/core/forms/templates/application_acl.pt
penelope/core/forms/templates/application_generic_view.pt
penelope/core/forms/templates/application_googledocument_view.pt
penelope/core/forms/templates/application_googlefolder_view.pt
penelope/core/forms/templates/application_show.pt
penelope/core/forms/templates/application_trac_report.pt
penelope/core/forms/templates/configurate_apps.pt
penelope/core/forms/templates/configuration.pt
penelope/core/forms/templates/contract_listing.pt
