Metadata-Version: 1.1
Name: penelope.core
Version: 2.1.46
Summary: Penelope main package
Home-page: http://getpenelope.github.com
Author: Penelope Team
Author-email: penelopedev@redturtle.it
License: UNKNOWN
Keywords: web wsgi bfg pylons pyramid
Platform: UNKNOWN
Classifier: Programming Language :: Python
Classifier: Framework :: Pylons
